{
  "dataset_iterator": {
    "name": "sqlite_iterator",
    "data_dir": "pmef",
    "shuffle": false,
    "data_url": "http://lnsigo.mipt.ru/export/datasets/drones.db"
  },
  "chainer": {
    "in": [
      "x"
    ],
    "out": [
      "y"
    ],
    "pipe": [
      {
        "name": "tfidf_ranker",
        "in": [
          "x"
        ],
        "out": [
          "y",
          "score"
        ],
        "fit_on_batch": [
          "x"
        ],
        "vectorizer": {
          "name": "hashing_tfidf_vectorizer",
          "fit_on_batch": [
            "x"
          ],
          "save_path": "pmef/drones_tfidf_matrix.npz",
          "load_path": "pmef/drones_tfidf_matrix.npz",
          "tokenizer": {
            "name": "stream_spacy_tokenizer",
            "lemmas": true,
            "ngram_range": [
              1,
              2
            ]
          }
        }
      }
    ]
  },
  "train": {
    "validate_best": false,
    "test_best": false,
    "batch_size": 10000
  },
  "metadata": {
    "download": [
      "http://lnsigo.mipt.ru/export/deeppavlov_data/pmef.tar.gz"
    ]
  }
}